leeno_mcp/__init__.py
leeno_mcp/__main__.py
leeno_mcp/config.py
leeno_mcp/server.py
leeno_mcp/connection/__init__.py
leeno_mcp/connection/document_pool.py
leeno_mcp/connection/leeno_macros.py
leeno_mcp/connection/uno_bridge.py
leeno_mcp/mocks/__init__.py
leeno_mcp/mocks/uno_mock.py
leeno_mcp/models/__init__.py
leeno_mcp/models/capitolo.py
leeno_mcp/models/contabilita.py
leeno_mcp/models/documento.py
leeno_mcp/models/prezzo.py
leeno_mcp/models/voce.py
leeno_mcp/tools/__init__.py
leeno_mcp/tools/analisi.py
leeno_mcp/tools/computo.py
leeno_mcp/tools/contabilita.py
leeno_mcp/tools/documents.py
leeno_mcp/tools/elenco_prezzi.py
leeno_mcp/tools/export.py
leeno_mcp/tools/giornale.py
leeno_mcp/tools/import_prezzi.py
leeno_mcp/tools/varianti.py
leeno_mcp/utils/__init__.py
leeno_mcp/utils/exceptions.py
leeno_mcp/utils/logging_config.py
leeno_mcp/wrappers/__init__.py
leeno_mcp/wrappers/analisi.py
leeno_mcp/wrappers/base.py
leeno_mcp/wrappers/computo.py
leeno_mcp/wrappers/contabilita.py
leeno_mcp/wrappers/document.py
leeno_mcp/wrappers/elenco_prezzi.py
leeno_mcp/wrappers/export.py
leeno_mcp/wrappers/giornale.py
leeno_mcp/wrappers/import_prezzi.py
leeno_mcp/wrappers/varianti.py
leeno_mcp-0.5.0.dist-info/METADATA
leeno_mcp-0.5.0.dist-info/WHEEL
leeno_mcp-0.5.0.dist-info/entry_points.txt
leeno_mcp-0.5.0.dist-info/licenses/LICENSE
leeno_mcp-0.5.0.dist-info/RECORD
