Metadata-Version: 2.4
Name: leeno-mcp
Version: 0.5.0
Summary: MCP Server for LeenO - Computi Metrici management through LibreOffice
Project-URL: Homepage, https://github.com/mikibart/leeno-mcp-server
Project-URL: Repository, https://github.com/mikibart/leeno-mcp-server.git
Project-URL: Documentation, https://github.com/mikibart/leeno-mcp-server#readme
Project-URL: Issues, https://github.com/mikibart/leeno-mcp-server/issues
Project-URL: Changelog, https://github.com/mikibart/leeno-mcp-server/blob/master/CHANGELOG.md
Author: LeenO Team
License-Expression: MIT
License-File: LICENSE
Keywords: ai-tools,building,computo,construction,estimate,leeno,libreoffice,mcp,metrico,quantity-surveying
Classifier: Development Status :: 4 - Beta
Classifier: Intended Audience :: Developers
Classifier: Intended Audience :: End Users/Desktop
Classifier: License :: OSI Approved :: MIT License
Classifier: Operating System :: OS Independent
Classifier: Programming Language :: Python :: 3
Classifier: Programming Language :: Python :: 3.10
Classifier: Programming Language :: Python :: 3.11
Classifier: Programming Language :: Python :: 3.12
Classifier: Topic :: Office/Business
Classifier: Topic :: Software Development :: Libraries :: Python Modules
Requires-Python: >=3.10
Requires-Dist: mcp<2.0.0,>=1.0.0
Requires-Dist: pydantic<3.0.0,>=2.0.0
Provides-Extra: dev
Requires-Dist: pytest-asyncio>=0.21.0; extra == 'dev'
Requires-Dist: pytest-cov>=4.0.0; extra == 'dev'
Requires-Dist: pytest>=7.0.0; extra == 'dev'
